{
  "name": "Solana Labs",
  "url": "https://solana.com/",
  "at": "hello",
  "building": "high-performance blockchain infrastructure",
  "products": [
    {
      "name": "Solana",
      "url": "https://solana.com/"
    }
  ],
  "socials": [
    "https://github.com/solana-labs",
    "https://twitter.com/solanalabs"
  ],
  "offices": [
    "chicago-illinois",
    "san-francisco-california"
  ],
  "headcount": 200,
  "founded": 2017,
  "jobs": [
    {
      "position": "full-stack-engineer",
      "level": "senior",
      "type": "full-time",
      "oss": true,
      "salary": {
        "amount": [
          130000,
          230000
        ],
        "range": "yearly",
        "currency": "usd"
      },
      "equity": [
        0.0,
        0.0
      ],
      "tech": [
        "postgresql",
        "next-js",
        "solana",
        "docker",
        "typescript",
        "aws",
        "rust",
        "react",
        "node-js",
        "gcp"
      ],
      "url": "https://boards.greenhouse.io/solana/jobs/4858813004"
    }
  ],
  "updated": "2023-07-02T21:41:36.069979Z"
}